funread/__init__.py
funread/legado/__init__.py
funread/legado/manage/__init__.py
funread/legado/manage/rss.py
funread/legado/manage/download/__init__.py
funread/legado/manage/download/base.py
funread/legado/manage/download/book.py
funread/legado/manage/download/generate.py
funread/legado/manage/download/rss.py
funread/legado/manage/utils/__init__.py
funread/legado/manage/utils/core.py
funread/scripts/__init__.py
funread/scripts/command.py
funread/web/__init__.py
funread/web/page/__init__.py
funread/web/page/video.py
funread/web/page/video_list.py
funread/web/parse/__init__.py
funread/web/parse/base.py
funread/web/parse/video.py
funread-1.1.39.dist-info/METADATA
funread-1.1.39.dist-info/WHEEL
funread-1.1.39.dist-info/licenses/LICENSE
funread-1.1.39.dist-info/RECORD
